sqlite_transform/__init__.py
sqlite_transform/cli.py
sqlite_transform-1.2.1.dist-info/LICENSE
sqlite_transform-1.2.1.dist-info/METADATA
sqlite_transform-1.2.1.dist-info/WHEEL
sqlite_transform-1.2.1.dist-info/entry_points.txt
sqlite_transform-1.2.1.dist-info/top_level.txt
sqlite_transform-1.2.1.dist-info/RECORD
