Metadata-Version: 2.1
Name: sqlite-transform
Version: 1.2.1
Summary: Tool for running transformations on columns in a SQLite database.
Home-page: https://github.com/simonw/sqlite-transform
Author: Simon Willison
License: Apache License, Version 2.0
Platform: UNKNOWN
Requires-Dist: dateutils
Requires-Dist: tqdm
Requires-Dist: click
Requires-Dist: sqlite-utils
Provides-Extra: test
Requires-Dist: pytest ; extra == 'test'
